CHANGELOG.rst
LICENSE
MANIFEST.in
README.rst
requirements.txt
setup.py
/Users/lsbardel/workspace/python-stdnet/extensions/src/cparser.cpp
docs/Makefile
docs/make.bat
docs/source/changelog.rst
docs/source/conf.py
docs/source/faq.rst
docs/source/index.rst
docs/source/overview.rst
docs/source/stdnetredis.rst
docs/source/api/fields.rst
docs/source/api/index.rst
docs/source/api/models.rst
docs/source/api/utility.rst
docs/source/backends/api.rst
docs/source/backends/index.rst
docs/source/backends/mongo.rst
docs/source/backends/redis.rst
docs/source/examples/asynchronous.rst
docs/source/examples/columnts.rst
docs/source/examples/index.rst
docs/source/examples/json.rst
docs/source/examples/local.rst
docs/source/examples/performance.rst
docs/source/examples/permissions.rst
docs/source/examples/primary.rst
docs/source/examples/query.rst
docs/source/examples/registration.rst
docs/source/examples/related.rst
docs/source/examples/search.rst
docs/source/examples/serialise.rst
docs/source/examples/sessions.rst
docs/source/examples/sorting.rst
docs/source/examples/structures.rst
docs/source/examples/tutorial.rst
docs/source/examples/twitter.rst
docs/source/examples/underscore.rst
extensions/__init__.py
extensions/setup.py
extensions/__pycache__/__init__.cpython-33.pyc
extensions/__pycache__/setup.cpython-33.pyc
extensions/src/common.pxd
extensions/src/cparser.pyx
extensions/src/parser.h
python_stdnet.egg-info/PKG-INFO
python_stdnet.egg-info/SOURCES.txt
python_stdnet.egg-info/dependency_links.txt
python_stdnet.egg-info/requires.txt
python_stdnet.egg-info/top_level.txt
stdnet/__init__.py
stdnet/apps/__init__.py
stdnet/apps/columnts/__init__.py
stdnet/apps/columnts/models.py
stdnet/apps/columnts/npts.py
stdnet/apps/columnts/redis.py
stdnet/apps/searchengine/__init__.py
stdnet/apps/searchengine/models.py
stdnet/apps/searchengine/processors/__init__.py
stdnet/apps/searchengine/processors/ignore.py
stdnet/apps/searchengine/processors/metaphone.py
stdnet/apps/searchengine/processors/porter.py
stdnet/backends/__init__.py
stdnet/backends/mongob/__init__.py
stdnet/backends/redisb/__init__.py
stdnet/backends/redisb/async.py
stdnet/backends/redisb/base.py
